MANIFEST.in
setup.cfg
setup.py
couchdb_cache/__init__.py
couchdb_cache/cache.py
couchdb_cache/exceptions.py
couchdb_cache/tests.py
django_couchdb_cache.egg-info/PKG-INFO
django_couchdb_cache.egg-info/SOURCES.txt
django_couchdb_cache.egg-info/dependency_links.txt
django_couchdb_cache.egg-info/not-zip-safe
django_couchdb_cache.egg-info/requires.txt
django_couchdb_cache.egg-info/top_level.txt
examples/test_project/manage.py
examples/test_project/requirements.txt
examples/test_project/test_project/__init__.py
examples/test_project/test_project/settings.py
examples/test_project/test_project/urls.py
examples/test_project/test_project/wsgi.py