Metadata-Version: 1.1
Name: django-couchdb-cache
Version: 0.1.2
Summary: CouchDB cache application for Django
Home-page: https://github.com/shuttlecloud/django-couchdb-cache.git
Author: ShuttleCloud Corp
Author-email: dev@shuttlecloud.com
License: UNKNOWN
Platform: UNKNOWN
Classifier: Development Status :: 4 - Beta
Classifier: Environment :: Console
Classifier: Intended Audience :: Developers
Classifier: License :: OSI Approved :: GNU General Public License v3 or later (GPLv3+)
Classifier: Programming Language :: Python :: 2
